setup.cfg
setup.py
ABOTP/__init__.py
ABOTP/client.py
ABOTP/server.py
ABOTP/storages.py
ABOTP/support.py
ABOTP.egg-info/PKG-INFO
ABOTP.egg-info/SOURCES.txt
ABOTP.egg-info/dependency_links.txt
ABOTP.egg-info/top_level.txt