Metadata-Version: 2.1
Name: ABOTP
Version: 2.1.1
Summary: Advanced bi-directional over TCP and UDP protocol
Author: mister_svinia
Author-email: i@savnil.ru
Classifier: Development Status :: 5 - Production/Stable
Classifier: Intended Audience :: Developers
Classifier: License :: OSI Approved :: MIT License
Requires-Python: >=3.10
